FSM Verilog with 2 always blocks/FSM Verilog with 2 always blocks.srcs/sources_1/new/preamble.v
module preamble (
    input clk,
    input rst,
    input start,
    output reg data_out
);


parameter IDLE = 4'b0000;  
parameter S0   = 4'b0001;  
parameter S1   = 4'b0010;  
parameter S2   = 4'b0011;  
parameter S3   = 4'b0100; 
parameter S4   = 4'b0101;  
parameter S5   = 4'b0110;  
parameter S6   = 4'b0111;  
parameter S7   = 4'b1000; 

reg [3:0] curr_state, next_state;


always @(curr_state, start) begin
    
    next_state = curr_state;
    data_out = 1'b0;
    
    case (curr_state)
        IDLE: begin
            data_out = 1'b0;
            if (start == 1'b1)
                next_state = S0;
            else
                next_state = IDLE;
        end
        
        S0: begin
            data_out = 1'b1;  
            next_state = S1;
        end
        
        S1: begin
            data_out = 1'b0;  
            next_state = S2;
        end
        
        S2: begin
            data_out = 1'b1;  
            next_state = S3;
        end
        
        S3: begin
            data_out = 1'b0; 
            next_state = S4;
        end
        
        S4: begin
            data_out = 1'b1;  
            next_state = S5;
        end
        
        S5: begin
            data_out = 1'b0;  
            next_state = S6;
        end
        
        S6: begin
            data_out = 1'b1;  
            next_state = S7;
        end
        
        S7: begin
            data_out = 1'b0;  
            next_state = IDLE; 
        end
        
    endcase
end


always @(posedge clk) begin
    if (rst == 1'b1)
        curr_state <= IDLE; 
    else
        curr_state <= next_state;
end

endmodule

FSM Verilog with 2 always blocks/FSM Verilog with 2 always blocks.srcs/sources_1/new/tb.v


`timescale 1ns/1ps

module tb_preamble_simple;


reg clk;
reg rst;
reg start;
wire data_out;


parameter CLK_PERIOD = 10;


preamble uut (
    .clk(clk),
    .rst(rst),
    .start(start),
    .data_out(data_out)
);


initial begin
    clk = 0;
    forever #(CLK_PERIOD/2) clk = ~clk;
end


initial begin
   
    rst = 1;
    start = 0;
    
   
    #(CLK_PERIOD * 2);
    
    
    rst = 0;
    #(CLK_PERIOD);
    
    
    $display("=== Verilog Preamble FSM Test Started ===");
    $display("Expected pattern: 10101010");
    
    
    $display("Starting preamble generation...");
    start = 1;
    #(CLK_PERIOD);
    start = 0;
    
    
    repeat(8) begin
        #(CLK_PERIOD);
        $display("Time: %0t ns, data_out = %b", $time, data_out);
    end
    
    
    #(CLK_PERIOD * 2);
    
    $display("=== Test Completed ===");
    $display("Check waveform for correct 10101010 pattern");
    
    
    $finish;
end


initial begin
    $dumpfile("preamble_fsm.vcd");
    $dumpvars(0, tb_preamble_simple);
end

endmodule

FSM Verilog with 2 always blocks/FSM Verilog with 2 always blocks.sim/sim_1/behav/xsim/preamble_fsm.vcd
$date
   Sun Jun 15 12:15:29 2025
$end

$version
  2024.1
  $dumpfile ("preamble_fsm.vcd") 
$end

$timescale
  1ps
$end

$scope module tb_preamble_simple $end
$var reg 1 ! clk $end
$var reg 1 " rst $end
$var reg 1 # start $end
$var wire 1 $ data_out $end
$scope module uut $end
$var wire 1 % clk $end
$var wire 1 & rst $end
$var wire 1 ' start $end
$var reg 1 ( data_out $end
$var reg 4 ) curr_state [3:0] $end
$var reg 4 * next_state [3:0] $end
$upscope $end
$upscope $end
$enddefinitions $end

#0
$dumpvars
0!
1"
0#
0$
0%
1&
0'
0(
bx )
bx *
$end

#5000
1!
1%
b0 )
b0 *

#10000
0!
0%

#15000
1!
1%

#20000
0!
0"
0%
0&

#25000
1!
1%

#30000
0!
1#
0%
1'
b1 *

#35000
1!
1$
1%
1(
b1 )
b10 *

#40000
0!
0#
0%
0'
1(
b10 *

#45000
1!
0$
1%
0(
b10 )
b11 *

#50000
0!
0%

#55000
1!
1$
1%
1(
b11 )
b100 *

#60000
0!
0%

#65000
1!
0$
1%
0(
b100 )
b101 *

#70000
0!
0%

#75000
1!
1$
1%
1(
b101 )
b110 *

#80000
0!
0%

#85000
1!
0$
1%
0(
b110 )
b111 *

#90000
0!
0%

#95000
1!
1$
1%
1(
b111 )
b1000 *

#100000
0!
0%

#105000
1!
0$
1%
0(
b1000 )
b0 *

#110000
0!
0%

#115000
1!
1%
b0 )

